{
  "all_selected_derivations_passed": true,
  "answers": {
    "can_offsets_be_reused_across_devices_on_same_build": "Only when the devices share the same effective dyld cache/linkedit and the full derived object compares identical. Same build alone is insufficient.",
    "can_offsets_be_reused_across_ios_18_builds": "No for full RCE/SBX tables. Absolute dyld/shared-cache offsets move across builds, including adjacent 18.6 patch builds.",
    "globally_reusable_offsets": "Only small structural constants and a subset of relative gadget offsets were stable in this selected set; not enough to reuse a global table.",
    "minimum_offset_index_key": "For RCE selection, use device/build key resolved via (iOS build + libsystem_pthread_linkedit) to a canonical device entry; chipset alone is not sufficient. SBX tables still need build-aware handling because message IDs/gadgets can shift by WebKit/build.",
    "when_is_linkedit_reuse_valid": "Reuse is valid only for a matching (iOS build, libsystem_pthread_linkedit) group after verifying the complete 105-field RCE object is identical across members. Linkedit collisions with differing full objects must stay separate."
  },
  "checks": [
    {
      "device_key": "iPhone11,8_22A3354",
      "ios": "18.0",
      "manual_offsets": 12,
      "missing_symbol_patterns": 0,
      "model_family_note": "A12-era",
      "rce_offsets": 105,
      "sbx0_offsets": 40,
      "sbx1_offsets": 24,
      "sources": {
        "manual": "ios18_manual_offsets_report.json",
        "rce": "ios18_rce_offset_candidates.json",
        "sbx": "ios18_sbx_offsets_report.json",
        "symbol": "ios18_symbol_offsets_report.json"
      },
      "tag": "22A3354__iPhone11,8"
    },
    {
      "device_key": "iPhone14,2_22B83",
      "ios": "18.1",
      "manual_offsets": 12,
      "missing_symbol_patterns": 0,
      "model_family_note": "A15-era",
      "rce_offsets": 105,
      "sbx0_offsets": 40,
      "sbx1_offsets": 24,
      "sources": {
        "manual": "ios18_extra_spotcheck_manual_offsets_report.json",
        "rce": "ios18_extra_spotcheck_rce_offset_candidates.json",
        "sbx": "ios18_extra_spotcheck_sbx_offsets_report.json",
        "symbol": "ios18_extra_spotcheck_symbol_offsets_report.json"
      },
      "tag": "22B83__iPhone14,2"
    },
    {
      "device_key": "iPhone17,1_22C152",
      "ios": "18.2",
      "manual_offsets": 12,
      "missing_symbol_patterns": 0,
      "model_family_note": "A18 Pro-era",
      "rce_offsets": 105,
      "sbx0_offsets": 40,
      "sbx1_offsets": 24,
      "sources": {
        "manual": "ios18_extra_spotcheck_manual_offsets_report.json",
        "rce": "ios18_extra_spotcheck_rce_offset_candidates.json",
        "sbx": "ios18_extra_spotcheck_sbx_offsets_report.json",
        "symbol": "ios18_extra_spotcheck_symbol_offsets_report.json"
      },
      "tag": "22C152__iPhone17,1"
    },
    {
      "device_key": "iPhone16,1_22D63",
      "ios": "18.3",
      "manual_offsets": 12,
      "missing_symbol_patterns": 0,
      "model_family_note": "A17 Pro-era",
      "rce_offsets": 105,
      "sbx0_offsets": 40,
      "sbx1_offsets": 24,
      "sources": {
        "manual": "ios18_spotcheck_manual_offsets_report.json",
        "rce": "ios18_spotcheck_rce_offset_candidates.json",
        "sbx": "ios18_spotcheck_sbx_offsets_report.json",
        "symbol": "ios18_spotcheck_symbol_offsets_report.json"
      },
      "tag": "22D63__iPhone16,1"
    },
    {
      "device_key": "iPhone12,8_22E240",
      "ios": "18.4",
      "manual_offsets": 12,
      "missing_symbol_patterns": 0,
      "model_family_note": "A13-era",
      "rce_offsets": 105,
      "sbx0_offsets": 40,
      "sbx1_offsets": 24,
      "sources": {
        "manual": "ios18_identity_184_manual_offsets_report.json",
        "rce": "ios18_identity_184_rce_offset_candidates.json",
        "sbx": "ios18_identity_184_sbx_offsets_report.json",
        "symbol": "ios18_identity_184_symbol_offsets_report.json"
      },
      "tag": "22E240__iPhone12,8"
    },
    {
      "device_key": "iPhone12,3_5_22E252",
      "ios": "18.4.1",
      "manual_offsets": 12,
      "missing_symbol_patterns": 0,
      "model_family_note": "A13-era grouped",
      "rce_offsets": 105,
      "sbx0_offsets": 40,
      "sbx1_offsets": 24,
      "sources": {
        "manual": "ios18_identity_184_manual_offsets_report.json",
        "rce": "ios18_identity_184_rce_offset_candidates.json",
        "sbx": "ios18_identity_184_sbx_offsets_report.json",
        "symbol": "ios18_identity_184_symbol_offsets_report.json"
      },
      "tag": "22E252__iPhone12,3"
    },
    {
      "device_key": "iPhone16,1_22F76",
      "ios": "18.5",
      "manual_offsets": 12,
      "missing_symbol_patterns": 0,
      "model_family_note": "A17 Pro-era",
      "rce_offsets": 105,
      "sbx0_offsets": 40,
      "sbx1_offsets": 24,
      "sources": {
        "manual": "ios18_identity_185_manual_offsets_report.json",
        "rce": "ios18_identity_185_rce_offset_candidates.json",
        "sbx": "ios18_identity_185_sbx_offsets_report.json",
        "symbol": "ios18_identity_185_symbol_offsets_report.json"
      },
      "tag": "22F76__iPhone16,1"
    },
    {
      "device_key": "iPhone16,1_22G86",
      "ios": "18.6",
      "manual_offsets": 12,
      "missing_symbol_patterns": 0,
      "model_family_note": "A17 Pro-era",
      "rce_offsets": 105,
      "sbx0_offsets": 40,
      "sbx1_offsets": 24,
      "sources": {
        "manual": "ios18_identity_186_manual_offsets_report.json",
        "rce": "ios18_identity_186_rce_offset_candidates.json",
        "sbx": "ios18_identity_186_sbx_offsets_report.json",
        "symbol": "ios18_identity_186_symbol_offsets_report.json"
      },
      "tag": "22G86__iPhone16,1"
    },
    {
      "device_key": "iPhone16,1_22G90",
      "ios": "18.6.1",
      "manual_offsets": 12,
      "missing_symbol_patterns": 0,
      "model_family_note": "A17 Pro-era",
      "rce_offsets": 105,
      "sbx0_offsets": 40,
      "sbx1_offsets": 24,
      "sources": {
        "manual": "ios18_identity_186_manual_offsets_report.json",
        "rce": "ios18_identity_186_rce_offset_candidates.json",
        "sbx": "ios18_identity_186_sbx_offsets_report.json",
        "symbol": "ios18_identity_186_symbol_offsets_report.json"
      },
      "tag": "22G90__iPhone16,1"
    },
    {
      "device_key": "iPhone16,1_22G100",
      "ios": "18.6.2",
      "manual_offsets": 12,
      "missing_symbol_patterns": 0,
      "model_family_note": "A17 Pro-era",
      "rce_offsets": 105,
      "sbx0_offsets": 40,
      "sbx1_offsets": 24,
      "sources": {
        "manual": "ios18_identity_186_manual_offsets_report.json",
        "rce": "ios18_identity_186_rce_offset_candidates.json",
        "sbx": "ios18_identity_186_sbx_offsets_report.json",
        "symbol": "ios18_identity_186_symbol_offsets_report.json"
      },
      "tag": "22G100__iPhone16,1"
    }
  ],
  "global_rce_stable_field_count": 22,
  "global_rce_stable_fields": [
    "CAPointer",
    "CGContextDelegate",
    "GPUConnectionToWebProcess_m_remoteGraphicsContextGLMap",
    "IOSurfaceContextDelegate",
    "IOSurfaceDrawable",
    "IOSurfaceQueue",
    "RemoteRenderingBackendProxy_off",
    "UI_m_connection",
    "m_backend",
    "m_drawingArea",
    "m_gpuProcessConnection",
    "m_gpuProcessConnection_m_identifier",
    "m_imageBuffer",
    "m_isRenderingSuspended",
    "m_platformContext",
    "m_remoteDisplayLists",
    "m_remoteRenderingBackendMap",
    "m_webProcessConnections",
    "privateState_off",
    "rxBufferMtl_off",
    "rxMtlBuffer_off",
    "vertexAttribVector_off"
  ],
  "global_rce_variable_field_count": 83,
  "linkedit_reuse_groups_observed": [
    {
      "all_full_rce_identical": true,
      "different": [],
      "ios": "18.0",
      "linkedit": "0x26bdc4000n",
      "tags": [
        "22A3354__iPhone17,3",
        "22A3354__iPhone17,4"
      ]
    },
    {
      "all_full_rce_identical": true,
      "different": [],
      "ios": "18.0",
      "linkedit": "0x26c420000n",
      "tags": [
        "22A3354__iPhone17,2",
        "22A3354__iPhone17,1"
      ]
    },
    {
      "all_full_rce_identical": true,
      "different": [],
      "ios": "18.1",
      "linkedit": "0x26ce08000n",
      "tags": [
        "22B83__iPhone12,3",
        "22B83__iPhone12,1"
      ]
    },
    {
      "all_full_rce_identical": true,
      "different": [],
      "ios": "18.2",
      "linkedit": "0x272bdc000n",
      "tags": [
        "22C152__iPhone13,4",
        "22C152__iPhone13,2_3"
      ]
    },
    {
      "all_full_rce_identical": true,
      "different": [],
      "ios": "18.2",
      "linkedit": "0x272cf8000n",
      "tags": [
        "22C152__iPhone15,4",
        "22C152__iPhone15,5"
      ]
    },
    {
      "all_full_rce_identical": true,
      "different": [],
      "ios": "18.2",
      "linkedit": "0x2736e0000n",
      "tags": [
        "22C152__iPhone15,3",
        "22C152__iPhone15,2"
      ]
    },
    {
      "all_full_rce_identical": true,
      "different": [],
      "ios": "18.3",
      "linkedit": "0x272aac000n",
      "tags": [
        "22D63__iPhone14,4",
        "22D63__iPhone14,5"
      ]
    },
    {
      "all_full_rce_identical": true,
      "different": [],
      "ios": "18.3",
      "linkedit": "0x272ea0000n",
      "tags": [
        "22D63__iPhone14,7",
        "22D63__iPhone14,8"
      ]
    },
    {
      "all_full_rce_identical": true,
      "different": [],
      "ios": "18.3",
      "linkedit": "0x2734dc000n",
      "tags": [
        "22D63__iPhone14,2",
        "22D63__iPhone14,3"
      ]
    },
    {
      "all_full_rce_identical": true,
      "different": [],
      "ios": "18.3",
      "linkedit": "0x274114000n",
      "tags": [
        "22D63__iPhone16,2",
        "22D63__iPhone16,1"
      ]
    },
    {
      "all_full_rce_identical": true,
      "different": [],
      "ios": "18.4",
      "linkedit": "0x27085c000n",
      "tags": [
        "22E240__iPhone12,1",
        "22E240__iPhone12,3"
      ]
    },
    {
      "all_full_rce_identical": true,
      "different": [],
      "ios": "18.4.1",
      "linkedit": "0x27085c000n",
      "tags": [
        "22E252__iPhone12,1",
        "22E252__iPhone12,3"
      ]
    }
  ],
  "objective": "Spot-check iOS 18.x offset identity/reuse assumptions without a full matrix, using read-only derivation reports.",
  "prompt_to_artifact_checklist": {
    "6_to_10_spot_checks": "10 selected records saved in ios18_identity_spotcheck_* reports.",
    "derivation_counts": "all_selected_derivations_passed is true; per-tag counts are in checks.",
    "identity_comparisons": "same_device_build_comparisons, same_build_cross_device_comparisons, and linkedit_reuse_groups_observed populated.",
    "main_builds_18_0_through_18_6_2": "Selected tags cover 22A3354, 22B83, 22C152, 22D63, 22E240, 22E252, 22F76, 22G86, 22G90, 22G100.",
    "separate_artifacts": "ios18_identity_spotcheck_symbol_offsets_report.json, ios18_identity_spotcheck_manual_offsets_report.json, ios18_identity_spotcheck_rce_offset_candidates.json, ios18_identity_spotcheck_sbx_offsets_report.json, ios18_identity_spotcheck_summary.json.",
    "varied_model_families": "Selected set covers A12-era, A13-era, A15-era, A17 Pro-era, and A18 Pro-era samples."
  },
  "same_build_cross_device_comparisons": [
    {
      "a": "22C152__iPhone16,1",
      "b": "22C152__iPhone17,1",
      "different": 3,
      "differing_fields": [
        "PerfPowerServicesReader_cstring",
        "__pthread_head",
        "libsystem_pthread_linkedit"
      ],
      "reason": "same build 18.2 across A17 Pro-era and A18 Pro-era",
      "same": 102,
      "total_common": 105
    },
    {
      "a": "22E240__iPhone12,3",
      "b": "22E240__iPhone12,8",
      "different": 35,
      "differing_fields": [
        "AVFAudio__AVLoadSpeechSynthesisImplementation_onceToken",
        "AVFAudio__OBJC_CLASS__AVSpeechSynthesisMarker",
        "AVFAudio__OBJC_CLASS__AVSpeechSynthesisProviderRequest",
        "AVFAudio__OBJC_CLASS__AVSpeechSynthesisVoice",
        "AVFAudio__OBJC_CLASS__AVSpeechUtterance",
        "CMPhoto__kCMPhotoTranscodeOption_Strips",
        "ImageIO__gFunc_CMPhotoCompressionCreateContainerFromImageExt",
        "ImageIO__gFunc_CMPhotoCompressionCreateDataContainerFromImage",
        "ImageIO__gFunc_CMPhotoCompressionSessionAddAuxiliaryImage",
        "ImageIO__gFunc_CMPhotoCompressionSessionAddAuxiliaryImageFromDictionaryRepresentation",
        "ImageIO__gFunc_CMPhotoCompressionSessionAddCustomMetadata",
        "ImageIO__gFunc_CMPhotoCompressionSessionAddExif",
        "PerfPowerServicesReader_cstring",
        "RemoteGraphicsContextGLWorkQueue",
        "WebCore__PAL_getPKContactClass",
        "WebCore__initPKContact_once",
        "WebCore__initPKContact_value",
        "WebCore__softLinkDDDFACacheCreateFromFramework",
        "WebCore__softLinkDDDFAScannerFirstResultInUnicharArray",
        "WebCore__softLinkMediaAccessibilityMACaptionAppearanceGetDisplayType",
        "WebProcess_singleton",
        "__pthread_head",
        "free_slabs",
        "gadget_control_1_ios184",
        "gadget_control_3_ios184",
        "gadget_loop_2_ios184",
        "gadget_set_all_registers_ios184",
        "libARI_cstring",
        "libGPUCompilerImplLazy__invoker",
        "libGPUCompilerImplLazy_cstring",
        "libsystem_c__atexit_mutex",
        "libsystem_pthread_base",
        "libsystem_pthread_linkedit",
        "mach_task_self_ptr",
        "pthread_create"
      ],
      "reason": "same build 18.4 across A13-era device groups",
      "same": 70,
      "total_common": 105
    },
    {
      "a": "22B83__iPhone12,3",
      "b": "22B83__iPhone12,8",
      "different": 36,
      "differing_fields": [
        "AVFAudio__AVLoadSpeechSynthesisImplementation_onceToken",
        "AVFAudio__OBJC_CLASS__AVSpeechSynthesisMarker",
        "AVFAudio__OBJC_CLASS__AVSpeechSynthesisProviderRequest",
        "AVFAudio__OBJC_CLASS__AVSpeechSynthesisVoice",
        "AVFAudio__OBJC_CLASS__AVSpeechUtterance",
        "CMPhoto__kCMPhotoTranscodeOption_Strips",
        "GetCurrentThreadTLSIndex_CurrentThreadIndex",
        "ImageIO__gFunc_CMPhotoCompressionCreateContainerFromImageExt",
        "ImageIO__gFunc_CMPhotoCompressionCreateDataContainerFromImage",
        "ImageIO__gFunc_CMPhotoCompressionSessionAddAuxiliaryImage",
        "ImageIO__gFunc_CMPhotoCompressionSessionAddAuxiliaryImageFromDictionaryRepresentation",
        "ImageIO__gFunc_CMPhotoCompressionSessionAddCustomMetadata",
        "ImageIO__gFunc_CMPhotoCompressionSessionAddExif",
        "PerfPowerServicesReader_cstring",
        "RemoteGraphicsContextGLWorkQueue",
        "WebCore__PAL_getPKContactClass",
        "WebCore__initPKContact_once",
        "WebCore__initPKContact_value",
        "WebCore__softLinkDDDFACacheCreateFromFramework",
        "WebCore__softLinkDDDFAScannerFirstResultInUnicharArray",
        "WebCore__softLinkMediaAccessibilityMACaptionAppearanceGetDisplayType",
        "WebProcess_singleton",
        "__pthread_head",
        "free_slabs",
        "gadget_control_1_ios184",
        "gadget_control_3_ios184",
        "gadget_loop_2_ios184",
        "gadget_set_all_registers_ios184",
        "libARI_cstring",
        "libGPUCompilerImplLazy__invoker",
        "libGPUCompilerImplLazy_cstring",
        "libsystem_c__atexit_mutex",
        "libsystem_pthread_base",
        "libsystem_pthread_linkedit",
        "mach_task_self_ptr",
        "pthread_create"
      ],
      "reason": "same build 18.1 across A13-era device groups",
      "same": 69,
      "total_common": 105
    }
  ],
  "same_device_build_comparisons": [
    {
      "a": "22F76__iPhone16,1",
      "b": "22G86__iPhone16,1",
      "different": 81,
      "differing_fields": [
        "AVFAudio__AVLoadSpeechSynthesisImplementation_onceToken",
        "AVFAudio__OBJC_CLASS__AVSpeechSynthesisMarker",
        "AVFAudio__OBJC_CLASS__AVSpeechSynthesisProviderRequest",
        "AVFAudio__OBJC_CLASS__AVSpeechSynthesisVoice",
        "AVFAudio__OBJC_CLASS__AVSpeechUtterance",
        "AVFAudio__cfstr_SystemLibraryTextToSpeech",
        "AXCoreUtilities__DefaultLoader",
        "CFNetwork__gConstantCFStringValueTable",
        "CMPhoto__CMPhotoCompressionCreateContainerFromImageExt",
        "CMPhoto__CMPhotoCompressionCreateDataContainerFromImage",
        "CMPhoto__CMPhotoCompressionSessionAddAuxiliaryImage",
        "CMPhoto__CMPhotoCompressionSessionAddAuxiliaryImageFromDictionaryRepresentation",
        "CMPhoto__CMPhotoCompressionSessionAddCustomMetadata",
        "CMPhoto__CMPhotoCompressionSessionAddExif",
        "CMPhoto__kCMPhotoTranscodeOption_Strips",
        "DesktopServicesPriv_bss",
        "GPUProcess_singleton",
        "GetCurrentThreadTLSIndex_CurrentThreadIndex",
        "HOMEUI_cstring",
        "ImageIO__IIOLoadCMPhotoSymbols",
        "ImageIO__gFunc_CMPhotoCompressionCreateContainerFromImageExt",
        "ImageIO__gFunc_CMPhotoCompressionCreateDataContainerFromImage",
        "ImageIO__gFunc_CMPhotoCompressionSessionAddAuxiliaryImage",
        "ImageIO__gFunc_CMPhotoCompressionSessionAddAuxiliaryImageFromDictionaryRepresentation",
        "ImageIO__gFunc_CMPhotoCompressionSessionAddCustomMetadata",
        "ImageIO__gFunc_CMPhotoCompressionSessionAddExif",
        "ImageIO__gImageIOLogProc",
        "JavaScriptCore__globalFuncParseFloat",
        "JavaScriptCore__jitAllowList",
        "JavaScriptCore__jitAllowList_once",
        "MediaAccessibility__MACaptionAppearanceGetDisplayType",
        "PerfPowerServicesReader_cstring",
        "RemoteGraphicsContextGLWorkQueue",
        "Security__SecKeychainBackupSyncable_block_invoke",
        "Security__SecOTRSessionProcessPacketRemote_block_invoke",
        "Security__gSecurityd",
        "TextToSpeech__OBJC_CLASS__TtC12TextToSpeech27TTSMagicFirstPartyAudioUnit",
        "WebCore__DedicatedWorkerGlobalScope_vtable",
        "WebCore__PAL_getPKContactClass",
        "WebCore__TelephoneNumberDetector_phoneNumbersScanner_value",
        "WebCore__ZZN7WebCoreL29allScriptExecutionContextsMapEvE8contexts",
        "WebCore__initPKContact_once",
        "WebCore__initPKContact_value",
        "WebCore__softLinkDDDFACacheCreateFromFramework",
        "WebCore__softLinkDDDFAScannerFirstResultInUnicharArray",
        "WebCore__softLinkMediaAccessibilityMACaptionAppearanceGetDisplayType",
        "WebCore__softLinkOTSVGOTSVGTableRelease",
        "WebProcess_ensureGPUProcessConnection",
        "WebProcess_gpuProcessConnectionClosed",
        "WebProcess_singleton",
        "__pthread_head",
        "dyld__RuntimeState_emptySlot",
        "dyld__RuntimeState_vtable",
        "dyld__dlopen_from_lambda_ret",
        "dyld__signPointer",
        "emptyString",
        "free_slabs",
        "gadget_control_1_ios184",
        "gadget_control_2_ios184",
        "gadget_control_3_ios184",
        "gadget_loop_1_ios184",
        "gadget_loop_2_ios184",
        "gadget_loop_3_ios184",
        "gadget_set_all_registers_ios184",
        "jsc_base",
        "libARI_cstring",
        "libGPUCompilerImplLazy__invoker",
        "libGPUCompilerImplLazy_cstring",
        "libdyld__dlopen",
        "libdyld__dlsym",
        "libdyld__gAPIs",
        "libsystem_c__atexit_mutex",
        "libsystem_kernel__thread_suspend",
        "libsystem_pthread_base",
        "libsystem_pthread_linkedit",
        "mach_task_self_ptr",
        "mainRunLoop",
        "pthread_create",
        "pthread_create_auth_stubs_offset",
        "pthread_create_jsc",
        "runLoopHolder_tid"
      ],
      "reason": "same device adjacent main builds 18.5 -> 18.6",
      "same": 24,
      "total_common": 105
    },
    {
      "a": "22G86__iPhone16,1",
      "b": "22G90__iPhone16,1",
      "different": 49,
      "differing_fields": [
        "AVFAudio__AVLoadSpeechSynthesisImplementation_onceToken",
        "AVFAudio__OBJC_CLASS__AVSpeechSynthesisMarker",
        "AVFAudio__OBJC_CLASS__AVSpeechSynthesisProviderRequest",
        "AVFAudio__OBJC_CLASS__AVSpeechSynthesisVoice",
        "AVFAudio__OBJC_CLASS__AVSpeechUtterance",
        "AVFAudio__cfstr_SystemLibraryTextToSpeech",
        "AXCoreUtilities__DefaultLoader",
        "CFNetwork__gConstantCFStringValueTable",
        "CMPhoto__kCMPhotoTranscodeOption_Strips",
        "DesktopServicesPriv_bss",
        "GPUProcess_singleton",
        "GetCurrentThreadTLSIndex_CurrentThreadIndex",
        "ImageIO__gFunc_CMPhotoCompressionCreateContainerFromImageExt",
        "ImageIO__gFunc_CMPhotoCompressionCreateDataContainerFromImage",
        "ImageIO__gFunc_CMPhotoCompressionSessionAddAuxiliaryImage",
        "ImageIO__gFunc_CMPhotoCompressionSessionAddAuxiliaryImageFromDictionaryRepresentation",
        "ImageIO__gFunc_CMPhotoCompressionSessionAddCustomMetadata",
        "ImageIO__gFunc_CMPhotoCompressionSessionAddExif",
        "ImageIO__gImageIOLogProc",
        "JavaScriptCore__jitAllowList",
        "JavaScriptCore__jitAllowList_once",
        "PerfPowerServicesReader_cstring",
        "RemoteGraphicsContextGLWorkQueue",
        "Security__gSecurityd",
        "TextToSpeech__OBJC_CLASS__TtC12TextToSpeech27TTSMagicFirstPartyAudioUnit",
        "WebCore__DedicatedWorkerGlobalScope_vtable",
        "WebCore__PAL_getPKContactClass",
        "WebCore__ZZN7WebCoreL29allScriptExecutionContextsMapEvE8contexts",
        "WebCore__initPKContact_once",
        "WebCore__initPKContact_value",
        "WebCore__softLinkDDDFACacheCreateFromFramework",
        "WebCore__softLinkDDDFAScannerFirstResultInUnicharArray",
        "WebCore__softLinkMediaAccessibilityMACaptionAppearanceGetDisplayType",
        "WebCore__softLinkOTSVGOTSVGTableRelease",
        "WebProcess_singleton",
        "__pthread_head",
        "dyld__RuntimeState_vtable",
        "emptyString",
        "free_slabs",
        "gadget_control_1_ios184",
        "gadget_control_3_ios184",
        "libGPUCompilerImplLazy__invoker",
        "libGPUCompilerImplLazy_cstring",
        "libdyld__gAPIs",
        "libsystem_c__atexit_mutex",
        "libsystem_pthread_linkedit",
        "mach_task_self_ptr",
        "mainRunLoop",
        "runLoopHolder_tid"
      ],
      "reason": "same device adjacent patch builds 18.6 -> 18.6.1",
      "same": 56,
      "total_common": 105
    },
    {
      "a": "22G90__iPhone16,1",
      "b": "22G100__iPhone16,1",
      "different": 0,
      "differing_fields": [],
      "reason": "same device adjacent patch builds 18.6.1 -> 18.6.2",
      "same": 105,
      "total_common": 105
    },
    {
      "a": "22D63__iPhone16,1",
      "b": "22F76__iPhone16,1",
      "different": 83,
      "differing_fields": [
        "AVFAudio__AVLoadSpeechSynthesisImplementation_onceToken",
        "AVFAudio__OBJC_CLASS__AVSpeechSynthesisMarker",
        "AVFAudio__OBJC_CLASS__AVSpeechSynthesisProviderRequest",
        "AVFAudio__OBJC_CLASS__AVSpeechSynthesisVoice",
        "AVFAudio__OBJC_CLASS__AVSpeechUtterance",
        "AVFAudio__cfstr_SystemLibraryTextToSpeech",
        "AXCoreUtilities__DefaultLoader",
        "CFNetwork__gConstantCFStringValueTable",
        "CMPhoto__CMPhotoCompressionCreateContainerFromImageExt",
        "CMPhoto__CMPhotoCompressionCreateDataContainerFromImage",
        "CMPhoto__CMPhotoCompressionSessionAddAuxiliaryImage",
        "CMPhoto__CMPhotoCompressionSessionAddAuxiliaryImageFromDictionaryRepresentation",
        "CMPhoto__CMPhotoCompressionSessionAddCustomMetadata",
        "CMPhoto__CMPhotoCompressionSessionAddExif",
        "CMPhoto__kCMPhotoTranscodeOption_Strips",
        "DesktopServicesPriv_bss",
        "Foundation__NSBundleTables_bundleTables_value",
        "GPUProcess_singleton",
        "GetCurrentThreadTLSIndex_CurrentThreadIndex",
        "HOMEUI_cstring",
        "ImageIO__IIOLoadCMPhotoSymbols",
        "ImageIO__gFunc_CMPhotoCompressionCreateContainerFromImageExt",
        "ImageIO__gFunc_CMPhotoCompressionCreateDataContainerFromImage",
        "ImageIO__gFunc_CMPhotoCompressionSessionAddAuxiliaryImage",
        "ImageIO__gFunc_CMPhotoCompressionSessionAddAuxiliaryImageFromDictionaryRepresentation",
        "ImageIO__gFunc_CMPhotoCompressionSessionAddCustomMetadata",
        "ImageIO__gFunc_CMPhotoCompressionSessionAddExif",
        "ImageIO__gImageIOLogProc",
        "JavaScriptCore__globalFuncParseFloat",
        "JavaScriptCore__jitAllowList",
        "JavaScriptCore__jitAllowList_once",
        "MediaAccessibility__MACaptionAppearanceGetDisplayType",
        "PerfPowerServicesReader_cstring",
        "RemoteGraphicsContextGLWorkQueue",
        "Security__SecKeychainBackupSyncable_block_invoke",
        "Security__SecOTRSessionProcessPacketRemote_block_invoke",
        "Security__gSecurityd",
        "TextToSpeech__OBJC_CLASS__TtC12TextToSpeech27TTSMagicFirstPartyAudioUnit",
        "WebCore__DedicatedWorkerGlobalScope_vtable",
        "WebCore__PAL_getPKContactClass",
        "WebCore__TelephoneNumberDetector_phoneNumbersScanner_value",
        "WebCore__ZZN7WebCoreL29allScriptExecutionContextsMapEvE8contexts",
        "WebCore__initPKContact_once",
        "WebCore__initPKContact_value",
        "WebCore__softLinkDDDFACacheCreateFromFramework",
        "WebCore__softLinkDDDFAScannerFirstResultInUnicharArray",
        "WebCore__softLinkMediaAccessibilityMACaptionAppearanceGetDisplayType",
        "WebCore__softLinkOTSVGOTSVGTableRelease",
        "WebProcess_ensureGPUProcessConnection",
        "WebProcess_gpuProcessConnectionClosed",
        "WebProcess_singleton",
        "__pthread_head",
        "dyld__RuntimeState_emptySlot",
        "dyld__RuntimeState_vtable",
        "dyld__dlopen_from_lambda_ret",
        "dyld__signPointer",
        "emptyString",
        "free_slabs",
        "gadget_control_1_ios184",
        "gadget_control_2_ios184",
        "gadget_control_3_ios184",
        "gadget_loop_1_ios184",
        "gadget_loop_2_ios184",
        "gadget_loop_3_ios184",
        "gadget_set_all_registers_ios184",
        "jsc_base",
        "libARI_cstring",
        "libGPUCompilerImplLazy__invoker",
        "libGPUCompilerImplLazy_cstring",
        "libdyld__dlopen",
        "libdyld__dlsym",
        "libdyld__gAPIs",
        "libsystem_c__atexit_mutex",
        "libsystem_kernel__thread_suspend",
        "libsystem_pthread_base",
        "libsystem_pthread_linkedit",
        "mach_task_self_ptr",
        "mainRunLoop",
        "pthread_create",
        "pthread_create_auth_stubs_offset",
        "pthread_create_jsc",
        "pthread_create_offset",
        "runLoopHolder_tid"
      ],
      "reason": "same device non-adjacent 18.3 -> 18.5",
      "same": 22,
      "total_common": 105
    },
    {
      "a": "22E240__iPhone12,8",
      "b": "22E252__iPhone12,3",
      "different": 37,
      "differing_fields": [
        "AVFAudio__AVLoadSpeechSynthesisImplementation_onceToken",
        "AVFAudio__OBJC_CLASS__AVSpeechSynthesisMarker",
        "AVFAudio__OBJC_CLASS__AVSpeechSynthesisProviderRequest",
        "AVFAudio__OBJC_CLASS__AVSpeechSynthesisVoice",
        "AVFAudio__OBJC_CLASS__AVSpeechUtterance",
        "AVFAudio__cfstr_SystemLibraryTextToSpeech",
        "CMPhoto__kCMPhotoTranscodeOption_Strips",
        "ImageIO__gFunc_CMPhotoCompressionCreateContainerFromImageExt",
        "ImageIO__gFunc_CMPhotoCompressionCreateDataContainerFromImage",
        "ImageIO__gFunc_CMPhotoCompressionSessionAddAuxiliaryImage",
        "ImageIO__gFunc_CMPhotoCompressionSessionAddAuxiliaryImageFromDictionaryRepresentation",
        "ImageIO__gFunc_CMPhotoCompressionSessionAddCustomMetadata",
        "ImageIO__gFunc_CMPhotoCompressionSessionAddExif",
        "PerfPowerServicesReader_cstring",
        "RemoteGraphicsContextGLWorkQueue",
        "WebCore__PAL_getPKContactClass",
        "WebCore__initPKContact_once",
        "WebCore__initPKContact_value",
        "WebCore__softLinkDDDFACacheCreateFromFramework",
        "WebCore__softLinkDDDFAScannerFirstResultInUnicharArray",
        "WebCore__softLinkMediaAccessibilityMACaptionAppearanceGetDisplayType",
        "WebProcess_singleton",
        "__pthread_head",
        "dyld__RuntimeState_vtable",
        "free_slabs",
        "gadget_control_1_ios184",
        "gadget_control_3_ios184",
        "gadget_loop_2_ios184",
        "gadget_set_all_registers_ios184",
        "libARI_cstring",
        "libGPUCompilerImplLazy__invoker",
        "libGPUCompilerImplLazy_cstring",
        "libsystem_c__atexit_mutex",
        "libsystem_pthread_base",
        "libsystem_pthread_linkedit",
        "mach_task_self_ptr",
        "pthread_create"
      ],
      "reason": "nearby A13-era devices across 18.4 -> 18.4.1",
      "same": 68,
      "total_common": 105
    }
  ],
  "script_notes": [
    "18.6+ SBX derivation exposed multi-hit gadget patterns for tcall_DSSG and tcall_DG; derive_ios18_sbx_offsets.py now selects the first deterministic hit for those patterns, matching existing handling for other multi-hit gadgets.",
    "Runtime JS tables were not patched as part of this identity spot-check aggregation."
  ],
  "selected_sample_count": 10,
  "selected_tags": [
    "22A3354__iPhone11,8",
    "22B83__iPhone14,2",
    "22C152__iPhone17,1",
    "22D63__iPhone16,1",
    "22E240__iPhone12,8",
    "22E252__iPhone12,3",
    "22F76__iPhone16,1",
    "22G86__iPhone16,1",
    "22G90__iPhone16,1",
    "22G100__iPhone16,1"
  ]
}
